MANIFEST.in
README
internal.c
internal.h
setup.cfg
setup.py
CDF.egg-info/PKG-INFO
CDF.egg-info/SOURCES.txt
CDF.egg-info/dependency_links.txt
CDF.egg-info/top_level.txt
cdf/__init__.py
cdf/attribute.py
cdf/entry.py
cdf/framework.py
cdf/interface.py
cdf/standard.py
cdf/typing.py
cdf/istp/__init__.py
cdf/istp/interface.py
cdf33-dist/samples/OperateAttributes.c
cdf33-dist/samples/OperateCDF.c
cdf33-dist/samples/OperateVariables.c
cdf33-dist/samples/example1.c
cdf33-dist/samples/read_example1.c
cdf33-dist/src/include/cdf.h
cdf33-dist/src/include/cdf2skt.h
cdf33-dist/src/include/cdfcmp.h
cdf33-dist/src/include/cdfconfig.h
cdf33-dist/src/include/cdfcvt.h
cdf33-dist/src/include/cdfdist.h
cdf33-dist/src/include/cdfdump.h
cdf33-dist/src/include/cdfedit.h
cdf33-dist/src/include/cdfinq.h
cdf33-dist/src/include/cdfirsdump.h
cdf33-dist/src/include/cdflib.h
cdf33-dist/src/include/cdflib64.h
cdf33-dist/src/include/cdfmd5.h
cdf33-dist/src/include/cdfmerge.h
cdf33-dist/src/include/cdfrev.h
cdf33-dist/src/include/cdfstats.h
cdf33-dist/src/include/cdftools.h
cdf33-dist/src/include/cdfvalidate.h
cdf33-dist/src/include/cdfxp.h
cdf33-dist/src/include/skt2cdf.h
cdf33-dist/src/include/widgets.h
cdf33-dist/src/include/windoz.h
cdf33-dist/src/lib/cdfalloc.c
cdf33-dist/src/lib/cdfalloc64.c
cdf33-dist/src/lib/cdfcks.c
cdf33-dist/src/lib/cdfclo.c
cdf33-dist/src/lib/cdfclo64.c
cdf33-dist/src/lib/cdfcon.c
cdf33-dist/src/lib/cdfcon64.c
cdf33-dist/src/lib/cdfcre.c
cdf33-dist/src/lib/cdfcre64.c
cdf33-dist/src/lib/cdfcsi.c
cdf33-dist/src/lib/cdfdel.c
cdf33-dist/src/lib/cdfdel64.c
cdf33-dist/src/lib/cdfed.c
cdf33-dist/src/lib/cdffii.c
cdf33-dist/src/lib/cdffsi.c
cdf33-dist/src/lib/cdffsi2.c
cdf33-dist/src/lib/cdffsi3.c
cdf33-dist/src/lib/cdfget.c
cdf33-dist/src/lib/cdfget64.c
cdf33-dist/src/lib/cdfgzip.c
cdf33-dist/src/lib/cdfgzip64.c
cdf33-dist/src/lib/cdfhuff.c
cdf33-dist/src/lib/cdfhuff64.c
cdf33-dist/src/lib/cdfhyper.c
cdf33-dist/src/lib/cdfhyper64.c
cdf33-dist/src/lib/cdflib.c
cdf33-dist/src/lib/cdfmd5.c
cdf33-dist/src/lib/cdfmem.c
cdf33-dist/src/lib/cdfmisc1.c
cdf33-dist/src/lib/cdfmisc1_64.c
