Metadata-Version: 1.1
Name: CDF
Version: 0.32
Summary: This package handles files in NASA Common Data Format
Home-page: http://efw.ssl.berkeley.edu/packages/cdf
Author: Matt Born
Author-email: mattborn@ssl.berkeley.edu
License: UNKNOWN
Platform: UNKNOWN
Classifier: Development Status :: 4 - Beta
Classifier: Intended Audience :: Science/Research
Classifier: License :: OSI Approved :: Apache Software License
Classifier: Topic :: Scientific/Engineering :: Astronomy
Requires: numpy (>=1.4)
